sequencing_table_one/__init__.py
sequecing_table_one-1.1.0.dist-info/METADATA
sequecing_table_one-1.1.0.dist-info/WHEEL
sequecing_table_one-1.1.0.dist-info/top_level.txt
sequecing_table_one-1.1.0.dist-info/RECORD
