Metadata-Version: 2.1
Name: sequecing-table-one
Version: 1.1.0
Home-page: 
Author: 
Author-email: 
Requires-Python: >=3.6
Requires-Dist: streamlit >=0.66
